fai/__init__.py
fai_ai-0.1.0.dist-info/licenses/LICENSE
fai_ai-0.1.0.dist-info/METADATA
fai_ai-0.1.0.dist-info/WHEEL
fai_ai-0.1.0.dist-info/top_level.txt
fai_ai-0.1.0.dist-info/RECORD
