Metadata-Version: 2.4
Name: fai-ai
Version: 0.1.0
Summary: Functional AI library.
Author-email: Greg Zozulin <gzozulin@gmail.com>
License: Apache-2.0
Requires-Python: >=3.8
License-File: LICENSE
Dynamic: license-file
